<?xml version="1.0" encoding="UTF-8"?>
<root><title>杭州招募“市民质量监督团”</title><source>http://jrzb.zjol.com.cn/html/2014-08/28/content_2802252.htm</source><newspaper>今日早报</newspaper><page>a0004版：新闻·民生</page><publishtime>2014-08-28</publishtime><crawltime>2014-08-28</crawltime><language>中文</language><encode>UTF-8</encode><body>
　　9月是第37个全国“质量月”
　　杭州招募“市民质量监督团”
　　□通讯员 杭质宣 本报记者 章高航
　　早报讯 今年9月将是第37个全国“质量月”，杭州市质监局将开展“智慧质监、质惠民生”主题活动，走入学校和社区宣传质量安全知识、提供部分产品质量免费检测服务，并从即日起征集市民代表加入“市民质量监督团”，走进杭州典型企业，了解产品质量控制和服务全过程，体验一次难忘的“质量监督之旅”。
　　当前杭产消费品质量怎么样，医疗设备计量是否准确……都是人们关心的内容。
　　质量月期间，杭州市质监局将开展一系列杭产消费品质量监督抽查，并发布产品质量监督抽查分析报告。
　　作为质量月的一大特色，本次活动将面向社会公开招募30位市民朋友，组成“市民质量监督团”，实地走进政府质量奖获奖企业，了解产品生产全过程，培养崇尚质量、监督质量、选择质量意识。
　　如果你想加入“市民质量监督团”，可拨打报名热线0571-85053917（周一周五09:00—18:00），报名时间截止9月10日。也可关注“杭州质监”官方微信，将姓名、联系电话发送至“杭州质监”微信公众号报名，或者以私信的方式将姓名、联系电话发送至“杭州质监”新浪微博进行报名。

</body></root>