<?xml version="1.0" encoding="UTF-8"?>

<root>
  <title>明日或反弹主力动向是关键</title>
  <source>http://gubushen1.blog.sohu.com/307275359.html</source>
  <publishdate>2014-12-24 14:56</publishdate>
  <crawldate>2015-01-26 11:39</crawldate>
  <content>证券股之前说过是二次减仓机会，现在看就是这么回事！如果一步到位拉升的太多，二次拉升幅度一定会减少，如果一拉升就下跌基本多是终结，虽然二次洗盘也有可能，但一般都要在掉头时二次出货观望！今日大盘大幅下跌是正常，好在个股有反弹，当然现在只能判断为是超跌引发的反弹，反弹能否持续还有待观察！就大盘而言这点跌幅还不足以改变，跌倒拉升启动位和前低点位正常会有反弹出现，进入反弹区间就看反弹！ 尾盘有资金进场抄底，跌到20日线上方出现反抽反弹都是正常现象！正常明日会有反弹出现，但要看主力动向，如果主力利用反弹积极出货，继续看跌，当然目前看主力利用反弹出货的概率还是比较大！如果没有反弹继续下跌，那大盘终结概率就增大。 主力操纵天天有，比如这几天主力一直在操纵的雷鸣科化，主力操纵股价走势进行出货。逆势操纵制造收阳强势假象，其实就是出货造！这种都是高控盘庄股，主力对倒收阳进行出货，这种货都是垃圾，基本属于涨也不要的垃圾股！ 只是分析不构成操作建议，股市永远存在例外，请勿按此操作，后果自负我不负！  发现把握价值请看教程专辑，一流投资课程！深度解析股价运行规律，主力操控规律，深度解析实战操作模式，把握经典实战操作盈利模式，请看详细内容介绍：股不神决胜股市终极课程：http://gubushen1.blog.sohu.com/306148305.html 更多分析敬请关注：微博：http://weibo.com/gubushen</content>
</root>
