<?xml version="1.0" encoding="UTF-8"?>

<root>
  <title>今天或再次上演跌停潮</title>
  <source>http://gubushen1.blog.sohu.com/307335885.html</source>
  <publishdate>2014-12-29 11:33</publishdate>
  <crawldate>2015-01-26 11:39</crawldate>
  <content>证券保险银行两桶油轮番轰炸，大盘今日再新高！不过今日是直接大幅高开，这不是正常现象！所以还是提防新高后抛货下跌。除非持有拉升的大盘股，其他股票还是减仓为主！前面也会所小盘股需要利用反弹出货，而不是再买入，现在看是对的。当下行情策略就是高抛低吸，调整结束可以买，高位掉头可以卖！ 目前大盘回落下跌是正常，利用高开出货再好不过！当然就目前大盘来说，还没有终结，终结需要持续抛空出货，虽然目前还没有出现，但主力抛空出货随时会出现！证券股出货已经比较充分了，基建铁路股出货也很充分了！现在就剩银行保险了，两桶油不是主力拉升的重点，只是操纵大盘和期指的工具而已，所以主力随时抛空出货就是正常！当然大盘终结需要持续多日的抛空出货，目前都没有出现，所以提防即可！今日或再次上演跌停潮，特别是开盘就跌的货，当然不会买，买了亏那是没事找抽！ 前面简单分析的几个股都是主力对倒操纵和对倒出货的股，这种股很多！虽然对倒有拉升的，当然也有出货的。所以拉升还可以投机，当然不搞最好，正常股不搞去搞对倒货不合理，对倒出货的当然要跑不能搞！还来看一个例子就是海陆重工，之前的拉升全是对倒操纵拉升，但最后也是对倒出货。高点是17.44，然后一字倒出货，今日继续下跌。 只是分析不构成操作建议，股市永远存在例外，请勿按此操作，后果自负我不负！  发现把握价值请看教程专辑，一流投资课程！深度解析股价运行规律，主力操控规律，深度解析实战操作模式，把握经典实战操作盈利模式，请看详细内容介绍：股不神决胜股市终极课程：http://gubushen1.blog.sohu.com/306148305.html 更多分析敬请关注：微博：http://weibo.com/gubushen</content>
</root>
