<url>http://bbs.iqilu.com/thread-14239395-1-4.html</url>
<title>广饶县对金岭化工等4环境违法企业实施停产治理 - 东营论坛 - 齐鲁社区 - 山东最大的城市生活社区,山东广播电视台官方社区!</title>
<div class="t_fsz"> 
 <table cellspacing="0" cellpadding="0">
  <tbody>
   <tr>
    <td class="t_f" id="postmessage_39408667"> <p style="line-height:25px;text-indent:nullem;text-align:left"><font style="color:rgb(51, 51, 51)"><font face="宋体, sans-serif, Arial">　东营<font color="#1e50a2"><a href="http://www.iqilu.com/" target="_blank">齐鲁网</a></font>讯（记者 陈海涛） 日前，东营市广饶县环保局加大了对企业环境违法行为查处力度，对查出的环境违法行为逐一进行限期治理或处罚，截止目前仍有4家企业经过治理后达不到治理要求。这是9月16日，记者跟随&quot;油城环保世纪行&quot;采访组到广饶县采访时了解到的。</font></font></p><p style="line-height:25px;text-indent:nullem;text-align:left"><font style="color:rgb(51, 51, 51)"><font face="宋体, sans-serif, Arial">　　<strong>正在停产治理的4家企业是：</strong></font></font></p><p style="line-height:25px;text-indent:nullem;text-align:left"><font style="color:rgb(51, 51, 51)"><font face="宋体, sans-serif, Arial"><strong>　　山东金岭化工股份有限公司</strong></font></font></p><p style="line-height:25px;text-indent:nullem;text-align:left"><font style="color:rgb(51, 51, 51)"><font face="宋体, sans-serif, Arial">　　环氧丙烷废水治理提标工程未完成，外排水质不稳定；热电脱销工程未完成，2台锅炉脱销工程至今未动工；固体废物处置、管理不规范。根据环保部门要求，该企业对环氧丙烷一期实施停产治理。</font></font></p><p style="line-height:25px;text-indent:nullem;text-align:left"><font style="color:rgb(51, 51, 51)"><font face="宋体, sans-serif, Arial">　　<strong>东营胜星化工有限公司</strong></font></font></p><p style="line-height:25px;text-indent:nullem;text-align:left"><font style="color:rgb(51, 51, 51)"><font face="宋体, sans-serif, Arial">　　南厂区项目经治理后仍然异味较大，严重影响周边环境。环保部门对南厂区项目实施停产治理，治理后达不到要求予以关停。</font></font></p><p style="line-height:25px;text-indent:nullem;text-align:left"><font style="color:rgb(51, 51, 51)"><font face="宋体, sans-serif, Arial">　　<strong>正和丙烯酸</strong></font></font></p><p style="line-height:25px;text-indent:nullem;text-align:left"><font style="color:rgb(51, 51, 51)"><font face="宋体, sans-serif, Arial">　　近期异味较大，造成城区大面积异味，附近居民反映强烈。环保部门要求其实施停产治理。</font></font></p><p style="line-height:25px;text-indent:nullem;text-align:left"><font style="color:rgb(51, 51, 51)"><font face="宋体, sans-serif, Arial">　　<strong>东方希望（东营）动物营养食品有限公司</strong></font></font></p><p style="line-height:25px;text-indent:nullem;text-align:left"><font style="color:rgb(51, 51, 51)"><font face="宋体, sans-serif, Arial">　　今年初该公司投资50余万元对异味进行了治理，异味扩散面积有所减小，但是由于距离居民区太近，仍对附近居民区及义乌批发市场有影响。环保部门要求其实施停产治理，并制订搬迁计划。</font></font></p><p style="line-height:25px;text-indent:nullem;text-align:left"><font style="color:rgb(51, 51, 51)"><font face="宋体, sans-serif, Arial">　　广饶县人民政府经研究，同意对山东金岭化工股份有限公司8万吨/年环氧丙烷、东营胜星化工有限公司2万吨/年芳烃油、正和集团股份有限公司4万吨/年丙烯酸、东方希望（东营）动物营养食品有限公司3万吨/年动物饲料等4个项目实施停产治理，以上项目所在乡镇（街道）、开发区收到批复后立即落实停产治理工作，停产治理项目待治理完成并通过验收后方可恢复生产。</font></font></p><br /> </td>
   </tr>
  </tbody>
 </table> 
</div>
<div class="t_fsz"> 
 <table cellspacing="0" cellpadding="0">
  <tbody>
   <tr>
    <td class="t_f" id="postmessage_39413077"> 好报道<img class="s" src="http://imgstore01.cdn.sogou.com/app/a/100520032/e179" smilieid="soso_e179" border="0" alt="" /><img src="static/image/smiley/cococat/53.gif" smilieid="360" border="0" alt="" /><img src="static/image/smiley/cococat/53.gif" smilieid="360" border="0" alt="" /><img src="static/image/smiley/cococat/53.gif" smilieid="360" border="0" alt="" /><img src="static/image/smiley/cococat/53.gif" smilieid="360" border="0" alt="" /></td>
   </tr>
  </tbody>
 </table> 
</div>
