<?xml version="1.0" encoding="UTF-8"?>
<root><title>新闻速览</title><source>http://epaper.bingtuannet.com/?id=97976</source><newspaper>兵团日报</newspaper><page>第05版：国内国际</page><publishtime>2014年8月12日 星期二</publishtime><crawltime>2014-08-12</crawltime><language>中文</language><encode>UTF-8</encode><body>
中央财政下达全国博物馆、纪念馆、美术馆等免费开放专项资金近50 亿元
财政部11 日发布消息，为支持构建现代公共文化服务体系，保障广大人民群众基本文化权益，中央财政下达了全国博物馆、纪念馆、美术馆、公共图书馆、文化馆（站）免费开放专项资金49.57亿元。
2014 年，上述专项资金共支持地方1815 个博物馆、纪念馆，1005 个市级和5542 个县级美术馆、公共图书馆和文化馆，以及34706 个乡镇文化站面向社会免费开放，并提供基本公共文化服务。
新疆314 国道中巴公路出现泥石流1 人遇难500 多辆车被困
10 日20 时许，新疆314 国道1570 公里路段处便道突发泥石流，致使1 人遇难、5 人受伤，至少500 多辆车因道路中断被困。
加沙地带第二次72 小时停火生效
由埃及提出的加沙地带第二次72 小时临时停火当地时间11日凌晨生效，巴勒斯坦和以色列谈判代表预计将于当天在开罗恢复长期停火谈判。
</body></root>