<?xml version="1.0" encoding="UTF-8"?>
<root><title>应急调水打通百万市民吃水“生命线”</title><source>http://dz.jjckb.cn/www/pages/webpage2009/html/2014-08/28/content_94870.htm</source><newspaper>经济参考</newspaper><page>第A05版：深度</page><publishtime>2014-08-28</publishtime><crawltime>2014-08-28</crawltime><language>中文</language><encode>UTF-8</encode><body>

    “我活了70年，从来没见过这么大的旱，大家对吃水很关心。前段时间一些地方限水，中午能来两个小时的水，最近供水情况好多了。”平顶山市市民刘林生对恢复供水颇有感触。
    今年以来，平顶山市遭受了建市以来最严重的旱情。全市143座水库有98座干涸，49条河道有44条断流，城区百万居民用水困难，主要水源地白龟山水库两次动用死库容，如果水位再降将威胁坝体安全。水库调水、节水限水、打井……各种手段都用上，只能支撑一个多月的用水。
    “水荒”步步紧逼。关键时刻，国家防总决定从8月6日开始，从丹江口水库通过南水北调中线总干渠向平顶山应急调水，调水规模2400万立方米，以确保3个月的供水，后期视情况再作调整。
    随着南水北调中线工程陶岔渠首闸门开启，清澈的汉江、丹江水流入干渠，在临时水泵的帮助下，清水一路北上，十几天时间走了约240公里路程。
    记者看到，在陶岔闸下游约700米处，水利部长江水利委员会汉江水文局的工作人员正在利用流速监测仪器监测水量。应急调水后，工作人员每天都要对引水和收水的水量、水质进行数次监测。监测显示，水质在二类以上。
    “在这次调水中，水源地克服了很大困难。”长委防办副主任陈敏告诉记者，今年汉江遭遇严重干旱，丹江口水库来水偏少，调水时水位是142.76米，按照南水北调工程调度方案，水位达到145米以上才能实施调水。“由于工程尚未正式通水，一些检测等还在进行中。”
    为了让水早日到达，应急调水采取自流和架设临时泵站并行的方式。丹江口水利枢纽电厂将发电量压缩到最低，全力保障调水。
    “往年丹江口电厂每年发电约38亿度，但今年由于来水偏少和确保应急调水，到现在发电总量只有8亿度。”汉江集团公司信息中心副主任王小牛说。
    连日来，在多部门的努力下，应急调水开始发挥效益。白龟山水库管理局局长苏嵌森介绍，调水之前水位每天下降3厘米，现在每天下降1厘米。
    截至8月25日8时，南水北调中线干渠向河南省平顶山市白龟山水库累计输水260万立方米。白龟山水库水位快速下降趋势得以遏制，城区百万人口用水困难有望缓解。
    “感谢”“感激”……这是采访中听到的平顶山市市民常说的话。当地一些干部表示，应急调水打通了百万市民吃水的“生命线”。
    平顶山市水利局副局长王保贵介绍说，下一步，平顶山市将在利用应急调水的基础上，加快燕山水库调水工程建设进度，研究水库水资源的多库联动。同时，加强节约用水，对用水大户采取限水措施，大力推广发电厂等使用中水，科学利用地下水源，引导企业和市民节约用水。
    “这次应急供水也带来一些启示，在极端天气灾害频发的情况下，必须加快完善各种引调水工程，确保互通、互济的城市供水格局。”王保贵表示，多个水源保障是城市的“定心丸”。此外，“开源”的同时更要“节流”，必须加快节水型社会建设，高效利用宝贵的水资源。

</body></root>