<?xml version="1.0" encoding="UTF-8"?>
<root><title>谁是南昌“地标楼盘” 南昌市最新楼盘标准地名公示</title><source>http://www.ncrbw.cn/html/2014-08/28/content_172107.htm</source><newspaper>南昌日报</newspaper><page>第07版：南昌楼市</page><publishtime>2014-08-28</publishtime><crawltime>2014-08-28</crawltime><language>中文</language><encode>UTF-8</encode><body>
  注：以下楼盘名单由南昌市地名委办公室提供，命名批准时间为2013年1月——2014年8月,本次活动原则上以上述楼盘为准,其它楼盘已经市地名办或县地名办备案的，需要参评者可另提申请,待活动组委会审核通过后另外公布。读者可根据自己掌握的情况，从中选出若干您认为称得上是"地标楼盘"的项目，通过本版公布的联系方式寄（传）或电邮给我们（名额不限）。每名参与者都有精美礼品相赠，凡选中5个以上者（经评选公布），本报另有奖品相赠。
</body></root>