<?xml version="1.0" encoding="UTF-8"?>
<root><title>五大服务体系 助推创业力量倍增</title><source>http://cqrbepaper.cqnews.net/cqrb/html/2014-08/13/content_1769212.htm</source><newspaper>重庆日报</newspaper><page>第008版： 区县</page><publishtime>2014-08-13</publishtime><crawltime>2014-08-13</crawltime><language>中文</language><encode>UTF-8</encode><body>

服务创业是园区的责任和使命。嘉陵三村·微企创业园五大服务体系的建立,成为助推微企创业力量的“倍增器”。
健全制度规定,实施规范服务。成立管理服务中心,制定有《创业孵化园企业培育制度》、《入孵创业项目评选办法》等制度,为规范化培育企业提供了重要保障。
搭建六大平台,突出精细服务。在社保服务、商标代理等10项服务基础上,搭建起了创业指导、政策帮扶等六大平台。3年来,累计为孵化企业争取创业补贴、小额担保贷款等共计1150多万元。2013年12月,《人民日报》进行了专题推介。
聘请管理团队,强化专业服务。引进专业的财务咨询公司、企业管理咨询公司为孵化企业提供个性化、针对性服务,帮扶初创企业迅速驶上发展“快车道”。
打造成长工场,提供增值服务。与重庆悦银中小企业公司合作建起了成长工场。孵化企业除享受原有的服务外,还能享受到悦银公司提供的投融资、商务助理等“升级”服务。政府促就业、民企得实惠、园区大发展“三赢”局面就此实现。
建社区工作站,推行延伸服务。利用街道主管园区的独特优势,在9个社区成立了工作站,促使一批“散落”在社区的创业企业快速成长、发展。
文/彭光灿 贺娜

</body></root>