<?xml version="1.0" encoding="UTF-8"?>
<root><title>7月中旬以来猪肉价格走高</title><source>http://bhsb.tjbhnews.com/html/2014-08/12/content_5_2.htm</source><newspaper>滨海时报</newspaper><page>第05版：经济</page><publishtime>2014-08-12</publishtime><crawltime>2014-08-12</crawltime><language>中文</language><encode>UTF-8</encode><body>　　据新华社全国农副产品和农资价格行情系统监测，与前一日相比，8月11日，猪肉、鸡蛋价格上涨；食用油价格以涨为主；成品粮价格稳中有涨；蔬菜、水果、水产品、牛羊肉价格微幅波动；奶类价格基本稳定。

　　监测的21种蔬菜中，6种价格上涨，4种价格下降，11种价格持平；猪后臀尖肉、猪五花肉价格均上涨0.1%；牛腱肉、去骨鲜羊肉价格上涨，带骨鲜羊肉价格下降，波动幅度均未超过0.1%，牛腩肉价格持平；普通鲜鸡蛋价格上涨0.3%，白条鸡价格持平；花生调和油、大豆调和油价格下降，纯花生油、纯菜籽油、纯大豆油、纯葵花籽油价格上涨，波动幅度均未超过0.1%。 
　　监测数据显示，7月中旬以来，全国猪肉价格整体呈上涨走势。与7月11日相比，8月11日，猪后臀尖肉和猪五花肉全国日均价涨幅均已经超过4.0%。分地区看，超九成省区市猪肉价格上涨，其中，黑龙江、重庆的猪后臀尖肉，黑龙江、广西、重庆的猪五花肉价格涨幅居前，在9.5%—11.0%之间。据新华社
</body></root>