<?xml version="1.0" encoding="UTF-8"?>
<root><title>“天使”能否拯救曼联</title><source>http://newspaper.jfdaily.com/jfrb/html/2014-08/28/content_10469.htm</source><newspaper>解放日报</newspaper><page>10版：文化・体育</page><publishtime>2014-08-28</publishtime><crawltime>2014-08-28</crawltime><language>中文</language><encode>UTF-8</encode><body>
    ■本报记者　秦东颖 
北京时间昨天凌晨，前皇马球星迪马利亚正式签约加盟曼联，并以5970万英镑创下英超转会费新纪录。但曼联球迷还没来得及为“天使”的到来庆祝，曼联就在联赛杯中0比4爆冷不敌英甲球队米尔顿凯恩斯。 
前两轮1平1负，曼联迎来20多年来的联赛最差开局，“神奇主帅”范加尔着实知道了英超不好混。 
南橘北枳。在荷兰队大显神威的352阵型，嫁接到曼联队结出的是酸涩的果实。如今的曼联后防线看似人员不少，但几乎都是刚刚由二线队提拔上来的小将。范加尔曾一手点亮了西多夫、克鲁伊维特、阿拉巴等小将的未来，他说：“不要对我说年轻人不能踢足球，只要找到合适的足球哲学，你可以做很多。”但在做到之前，曼联可能需要付出更多的学费。 
迪马利亚的到来，可解范加尔燃眉之急。这位“阿根廷飞翼”在本菲卡和皇马的中场都有上佳表现，是一位多面手。在范加尔的352阵型里，迪马利亚既可以充当“曼联的罗本”，也可以串联中前场，就像当年吉格斯所做的一样，从而梳理“红魔”目前凌乱的进攻。 
然而必须看到，曼联目前问题的症结还是在中后场。迪马利亚的加盟固然为曼联打了一针强心剂，但他不能解决曼联的防守难题。曼联更需要像布来恩・罗布森和罗伊・基恩这种攻守兼备、作风硬朗的球员。据悉，曼联目前正在积极运作尤文的比达尔加盟。 
范加尔的英超执教生涯前途未卜，但他比前任莫耶斯幸运的是，辉煌的教练履历会帮助他获得更多的适应时间。
</body></root>