<?xml version="1.0" encoding="UTF-8"?>
<root><title>户口不在海口准生证咋办</title><source>http://szb.hkwb.net/szb/html/2014-08/28/content_13523.htm</source><newspaper>海口晚报</newspaper><page>06版：民生</page><publishtime>2014-08-28</publishtime><crawltime>2014-08-28</crawltime><language>中文</language><encode>UTF-8</encode><body>
　　
　　tyf123：听说海南办理准生证有新政策，程序简化了不少，我想咨询下我这种情况现在办理准生证的流程是怎样的？我和我老婆现在常住、工作在海口，我的户口在海口，我老婆的户口是在海口上完大学后再转回到下面县市去了，现在我在海口要如何办理准生证？还需要到我老婆的户口所在地盖章吗？因为过三四个月就要生了，所以比较着急。
　　市人口和计划生育委员会答复：你好！办理一孩《生育服务证》可到您现居住地居委会或街道办领表申请、办理。携带夫妻双方单位出具《婚育证明》，需带上双方结婚证、户口本、身份证、女方一寸相片2张。    (记者余加亮)
</body></root>