<?xml version="1.0" encoding="UTF-8"?>
<root><title>郭义文母子写来感谢信</title><source>http://szb.hkwb.net/szb/html/2014-08/28/content_13532.htm</source><newspaper>海口晚报</newspaper><page>06版：民生</page><publishtime>2014-08-28</publishtime><crawltime>2014-08-28</crawltime><language>中文</language><encode>UTF-8</encode><body>

　　本报24小时新闻热线66812555消息（记者高潮）8月 27日，郭义文和母亲袁海燕将一份感谢信送到海口晚报社，感谢本报对郭义文的帮助，帮郭义文筹到了26500元，解决了他的学费问题。
　　“郭义文现在上学的费用有着落了，全靠海口晚报的帮忙，今天我们特意来送感谢信感谢。”上午10时许，袁海燕将手写的感谢信递到了社会新闻部负责人手中，感谢本报对郭义文的关注，爱心人士给郭义文捐款26500元，解决了郭义文今年的报名费。9月2日，郭义文就要前往北京，准备到北京大学报到。郭义文表示在大学期间要一心一意学习，提高学习成绩，争取读研究生继续深造，待学业有成，一定报效祖国和家乡，报答资助他上学的人士。
　　
　　尊敬的海口晚报新闻热线：
　　近日，我就要赴北京大学就读。由于家庭的困境，我得到了热心的海口晚报新闻记者的报料，还有社会各界热心人士的资助，以及父老乡亲的帮助。学费已经有着落。在这里我表示衷心地感谢。有了你们的帮助和支持，我会在以后的学业里一定刻苦攻读，待学业有成，定要报效祖国和家乡，报答资助我上学的热心人士！祝你们一生平安！
</body></root>