<url>http://club.dzwww.com/thread-45587569-1-2.html</url>
<title>菏泽路海信·天鹅湖北门菏泽路已经有人在清理了~ - 东营论坛 - 大众论坛</title>
<div class="t_fsz"> 
 <table cellspacing="0" cellpadding="0">
  <tbody>
   <tr>
    <td class="t_f" id="postmessage_78492150"> <p align="left">&nbsp; &nbsp; 昨晚看到有人在论坛发帖称在海信&middot;天鹅湖北门菏泽路附近，这块的垃圾碎石已经好几天没人清理了。今天上午，偶然路过经过那里，看到已经有人员在清理这些砂石了，这些人称自己是附近恒信物业的工作人员，看到这里砂石的情况，便自发前来清理。其中一个人说，有一些装着垃圾的大车晚上偷偷运垃圾，垃圾中途掉了也不管，很让人无奈呀。&nbsp;&nbsp;给这俩人点赞有木有~</p><p align="center"> 
      <ignore_js_op> 
       <img id="aimg_9054359" src="static/image/common/none.gif" zoomfile="http://att1.dzwww.com/forum/201410/29/1439470b27s2cebshh74wb.jpg" file="http://att1.dzwww.com/forum/201410/29/1439470b27s2cebshh74wb.jpg" class="zoom" onclick="zoom(this, this.src)" width="750" inpost="1" alt="IMG_7962.JPG" title="IMG_7962.JPG" /> 
      </ignore_js_op></p>
     <div class="tip tip_4 aimg_tip" id="aimg_9054359_menu" style="position: absolute; display: none"> 
      <div class="tip_c xs0"> 
       <div class="y">
        2014-10-29 14:39 上传
       </div> 
       <a href="forum.php?mod=attachment&amp;aid=OTA1NDM1OXxhMDYxNGJlZnwxNDE1MDIyMDgxfDB8NDU1ODc1Njk%3D&amp;nothumb=yes" title="IMG_7962.JPG 下载次数:0" target="_blank"><strong>下载附件</strong> <span class="xs0">(232.48 KB)</span></a> 
      </div> 
      <div class="tip_horn"></div> 
     </div>  <p></p><p align="center"> 
      <ignore_js_op> 
       <img id="aimg_9054361" src="static/image/common/none.gif" zoomfile="http://att1.dzwww.com/forum/201410/29/144124erkjp4j8w2rxrkle.jpg" file="http://att1.dzwww.com/forum/201410/29/144124erkjp4j8w2rxrkle.jpg" class="zoom" onclick="zoom(this, this.src)" width="750" inpost="1" alt="IMG_7967.JPG" title="IMG_7967.JPG" /> 
      </ignore_js_op></p>
     <div class="tip tip_4 aimg_tip" id="aimg_9054361_menu" style="position: absolute; display: none"> 
      <div class="tip_c xs0"> 
       <div class="y">
        2014-10-29 14:41 上传
       </div> 
       <a href="forum.php?mod=attachment&amp;aid=OTA1NDM2MXxmMjY4YWI4YXwxNDE1MDIyMDgxfDB8NDU1ODc1Njk%3D&amp;nothumb=yes" title="IMG_7967.JPG 下载次数:1" target="_blank"><strong>下载附件</strong> <span class="xs0">(229.23 KB)</span></a> 
      </div> 
      <div class="tip_horn"></div> 
     </div>  <p></p><br /> </td>
   </tr>
  </tbody>
 </table> 
</div>
