<?xml version="1.0" encoding="UTF-8"?>
<root><title>三都一村寨为本村孩子建起“教育基金会”—— 乡亲“凑份子” 助学子读书 八年资助72名村里娃，部分获助学生毕业后开始反哺家乡</title><source>http://epaper.gywb.cn/gywb/html/2014-08/27/content_400873.htm</source><newspaper>贵阳晚报</newspaper><page>第A11版：市州新闻</page><publishtime>2014-08-27</publishtime><crawltime>2014-08-28</crawltime><language>中文</language><encode>UTF-8</encode><body>
8月20日，三都水族自治县达便村，今年考取大学的4名大学生及位列全县中考成绩前100名的四名中学生，分别得到村里教育基金会的1000元或500元的奖学助学金。
  至此，8年时间，村里基金会已发放助学基金12万元，资助大学生46人、品学兼优的初、高中生26人。
  
  
  
  A
  返乡农民工
  带头建基金
  达便村地处三都水族自治县水族聚居区腹地，距县城30公里，全村共有9个村民组1800余人。
  42岁的潘大典是当地一位村民。因家庭困难，初中未毕业，他就辍学外出打工了。有感于没文化之苦，2006年返乡后，他捐出辛苦挣来的1万元，在团县委春晖行动2万元活动经费的支持下，成立了达便村教育基金会。
  “建起这个基金，是希望村里的孩子都有学上、有书读，没有后顾之忧，最终能在村里营造一个良好的读书氛围。”潘大典说。
  有感于他的影响，很多村民纷纷加入到凑份子的行列，50元、100元……就连当地乡干部与村里在外打工的村民也纷纷参与进来。
  年近70岁的潘子勇老人，是当地的一个五保户，虽没子嗣，靠救济金生活，每年仍要捐款。“50元不多，算我一份心意。”老人说。
  
  
  
  B
  8年时间
  助学72人
  据悉，达便村教育基金会的资金来源，主要靠村民们自愿凑份子以及社会捐款这两大渠道。
  从2006年成立基金会至今，该基金会已收到村民及社会各界人士助学基金近15万元。
  根据基金会的规定，达便村籍学生凡考取重点大学的（清华、北大、港大及香港科技大学）的，一次性奖励10000元；考取985工程院校（含预科）的，一次性奖励5000元，考取211工程院校（含预科）的，一次性奖励3000元，考取普通一本（含预科）的，一次性奖励2000元；考取二本（含预科）的，一次性奖励1000元。在县内就读的中学生，中考总成绩在全县排名前100名的，一次性奖励500元。其中，凡双农家庭的学生，在原来奖励的基础上加奖50%。
  据悉，在基金会的激励和帮助下，这个由村民自发组织的教育基金会，从2006年至今，8年时间共发放了12万元助学基金，已资助大学生46人、品学兼优的初、高中生26人。
  
  
  
  C
  当年受助学生
  开始反哺家乡
  据介绍，在该基金会的努力下，达便村的文化人渐渐多了起来，从村里走出去的大学生一年比一年多，部分学生毕业后，开始反过来支持基金会的工作，反哺家乡、奉献社会，积极参加爱心公益活动。
  潘远逑是2007年考取凯里学院的学生，当年获得基金会的帮助后，家庭困难的他顺利完成了学业。毕业后，他回到三都县工作，每年除向基金会捐款400元以外，还积极参加村里的其他公益活动。
  目前，受助的学生毕业后反哺家乡的大学生已达32人，高中生11人。如今，这个地处贵州腹地的普通水族村寨，由于有了这个教育基金，虽不富裕却声名远播。 张仁东 张奕
  
  
  


<img>http://epaper.gywb.cn/gywb/res/1/41/2014-08/27/A11/res01_attpic_brief.jpg</img></body></root>